influxio/__init__.py
influxio/adapter.py
influxio/cli.py
influxio/core.py
influxio/io.py
influxio/model.py
influxio/testdata.py
influxio/util/__init__.py
influxio/util/cli.py
influxio/util/common.py
influxio/util/compat.py
influxio/util/db.py
influxio/util/pandas.py
influxio/util/report.py
influxio-0.6.1.dist-info/licenses/LICENSE
influxio-0.6.1.dist-info/METADATA
influxio-0.6.1.dist-info/WHEEL
influxio-0.6.1.dist-info/entry_points.txt
influxio-0.6.1.dist-info/top_level.txt
influxio-0.6.1.dist-info/RECORD
