Metadata-Version: 2.4
Name: influxio
Version: 0.6.1
Summary: Import and export data into/from InfluxDB
Author-email: Andreas Motl <andreas.motl@panodata.org>, Richard Pobering <richard.pobering@panodata.org>
License: MIT
Project-URL: changelog, https://github.com/daq-tools/influxio/blob/main/CHANGES.rst
Project-URL: documentation, https://github.com/daq-tools/influxio
Project-URL: homepage, https://github.com/daq-tools/influxio
Project-URL: repository, https://github.com/daq-tools/influxio
Keywords: export,ilp,import,influx,influxdb,line-protocol,lineprotocol,rdbms,sql,sqlalchemy,timeseries,timeseries-data,transfer
Classifier: Development Status :: 4 - Beta
Classifier: Environment :: Console
Classifier: Intended Audience :: Customer Service
Classifier: Intended Audience :: Developers
Classifier: Intended Audience :: Education
Classifier: Intended Audience :: End Users/Desktop
Classifier: Intended Audience :: Information Technology
Classifier: Intended Audience :: Manufacturing
Classifier: Intended Audience :: Science/Research
Classifier: Intended Audience :: System Administrators
Classifier: Intended Audience :: Telecommunications Industry
Classifier: License :: OSI Approved :: MIT License
Classifier: Operating System :: MacOS :: MacOS X
Classifier: Operating System :: Microsoft :: Windows
Classifier: Operating System :: POSIX :: Linux
Classifier: Operating System :: Unix
Classifier: Programming Language :: Python
Classifier: Programming Language :: Python :: 3 :: Only
Classifier: Programming Language :: Python :: 3.8
Classifier: Programming Language :: Python :: 3.9
Classifier: Programming Language :: Python :: 3.10
Classifier: Programming Language :: Python :: 3.11
Classifier: Programming Language :: Python :: 3.12
Classifier: Programming Language :: Python :: 3.13
Classifier: Programming Language :: Python :: 3.14
Classifier: Topic :: Communications
Classifier: Topic :: Database
Classifier: Topic :: Documentation
Classifier: Topic :: Education
Classifier: Topic :: File Formats
Classifier: Topic :: Office/Business
Classifier: Topic :: Scientific/Engineering
Classifier: Topic :: Scientific/Engineering :: Human Machine Interfaces
Classifier: Topic :: Scientific/Engineering :: Information Analysis
Classifier: Topic :: Scientific/Engineering :: Interface Engine/Protocol Translator
Classifier: Topic :: Software Development :: Libraries
Classifier: Topic :: Software Development :: Testing
Classifier: Topic :: Software Development :: Version Control
Classifier: Topic :: System :: Archiving
Classifier: Topic :: System :: Logging
Classifier: Topic :: System :: Monitoring
Classifier: Topic :: System :: Networking
Classifier: Topic :: System :: Recovery Tools
Classifier: Topic :: System :: Systems Administration
Classifier: Topic :: Text Processing
Classifier: Topic :: Utilities
Requires-Python: >=3.8
License-File: LICENSE
Requires-Dist: click<9
Requires-Dist: colorama<1
Requires-Dist: cratedb-toolkit
Requires-Dist: dask[dataframe]>=2020
Requires-Dist: fsspec[http,s3]
Requires-Dist: importlib-metadata; python_version <= "3.9"
Requires-Dist: influx-line==1.0.0
Requires-Dist: influxdb-client[ciso]<2
Requires-Dist: line-protocol-parser<2
Requires-Dist: pandas<2.4
Requires-Dist: polars<2
Requires-Dist: psycopg2-binary<3
Requires-Dist: pueblo>=0.0.7
Requires-Dist: pyarrow; python_version <= "3.9"
Requires-Dist: sqlalchemy-cratedb<1,>=0.37
Requires-Dist: sqlalchemy-utils<0.43
Requires-Dist: universal-pathlib<0.4
Requires-Dist: yarl<2
Provides-Extra: develop
Requires-Dist: black<26; extra == "develop"
Requires-Dist: mypy<1.19; extra == "develop"
Requires-Dist: poethepoet<1; extra == "develop"
Requires-Dist: pyproject-fmt<3; extra == "develop"
Requires-Dist: ruff<0.15; extra == "develop"
Requires-Dist: sphinx-autobuild; extra == "develop"
Requires-Dist: validate-pyproject<1; extra == "develop"
Provides-Extra: docs
Requires-Dist: furo; extra == "docs"
Requires-Dist: myst-parser[linkify]<5,>=0.18; extra == "docs"
Requires-Dist: sphinx<9; extra == "docs"
Requires-Dist: sphinx-copybutton; extra == "docs"
Requires-Dist: sphinx-design-elements<1; extra == "docs"
Requires-Dist: sphinxcontrib-mermaid<2; extra == "docs"
Requires-Dist: sphinxext-opengraph<1; extra == "docs"
Provides-Extra: release
Requires-Dist: build<2; extra == "release"
Requires-Dist: twine<7; extra == "release"
Provides-Extra: test
Requires-Dist: pytest<9; extra == "test"
Requires-Dist: pytest-cov<8; extra == "test"
Dynamic: license-file
